README.md
setup.py
example12121.egg-info/PKG-INFO
example12121.egg-info/SOURCES.txt
example12121.egg-info/dependency_links.txt
example12121.egg-info/top_level.txt
example_pkg/__init__.py