Metadata-Version: 2.1
Name: example12121
Version: 0.0.3
Summary: A small example package
Home-page: UNKNOWN
Author: jinzening
Author-email: zening918@163.com
License: UNKNOWN
Platform: UNKNOWN
Classifier: Programming Language :: Python :: 3
Classifier: License :: OSI Approved :: MIT License
Classifier: Operating System :: OS Independent
Requires-Python: >=3.6
